[
  {
    "event_id": "86a37e4f-28d2-49fd-82dc-29afe46a5747",
    "session_id": "00a83c2f-a276-413c-8e59-4e3f9f49726b",
    "run_id": "430562ad-46d6-47d4-b61b-1ab4d610b826",
    "correlation_id": "58c60067-38f9-4b2a-9b9a-a2246172709e",
    "timestamp": "2026-03-23T20:39:00Z",
    "strategy": "scalping",
    "strategy_version": "v2",
    "mode": "paper",
    "broker_mode": "alpaca_paper_api",
    "symbol": "NFLX",
    "side_considered": "buy",
    "bracket_considered": false,
    "signal_source": "qlib_candidate_only",
    "qlib_raw_score": 0.002166131947381391,
    "predicted_return": 0.002166131947381391,
    "target_return": 0.002166131947381391,
    "candidate_rank": 1,
    "prediction_artifact_path": "C:\\Users\\User\\Documents\\MyTradingBot_Next\\models\\predictions\\latest.json",
    "model_artifact_path": "C:\\Users\\User\\Documents\\MyTradingBot_Next\\models\\qlib\\model.pkl",
    "dataset_artifact_path": "C:\\Users\\User\\Documents\\MyTradingBot_Next\\data\\qlib\\dataset.parquet",
    "source_data_timestamp": "2026-03-23T20:39:00Z",
    "source_data_freshness_minutes": 0,
    "rule_checks": [
      {
        "stage": "freshness",
        "name": "predictions_fresh",
        "passed": true,
        "detail": null,
        "value": null
      },
      {
        "stage": "freshness",
        "name": "market_snapshot_fresh",
        "passed": true,
        "detail": null,
        "value": null
      },
      {
        "stage": "strategy",
        "name": "duplicate_position_check",
        "passed": true,
        "detail": null,
        "value": null
      },
      {
        "stage": "strategy",
        "name": "foreign_position_check",
        "passed": true,
        "detail": null,
        "value": null
      },
      {
        "stage": "strategy",
        "name": "cooldown_check",
        "passed": true,
        "detail": null,
        "value": null
      },
      {
        "stage": "strategy",
        "name": "confidence_threshold",
        "passed": false,
        "detail": null,
        "value": null
      },
      {
        "stage": "strategy",
        "name": "cooldown_logic",
        "passed": true,
        "detail": null,
        "value": null
      },
      {
        "stage": "strategy",
        "name": "duplicate_position",
        "passed": true,
        "detail": null,
        "value": null
      },
      {
        "stage": "strategy",
        "name": "flatten_near_close_logic",
        "passed": true,
        "detail": null,
        "value": null
      },
      {
        "stage": "strategy",
        "name": "intraday_volatility_regime",
        "passed": true,
        "detail": null,
        "value": null
      },
      {
        "stage": "strategy",
        "name": "liquidity_filter",
        "passed": false,
        "detail": null,
        "value": null
      },
      {
        "stage": "strategy",
        "name": "liquidity_stress_filter",
        "passed": true,
        "detail": null,
        "value": null
      },
      {
        "stage": "strategy",
        "name": "liquidity_sweep_detection",
        "passed": true,
        "detail": null,
        "value": null
      },
      {
        "stage": "strategy",
        "name": "order_book_imbalance",
        "passed": false,
        "detail": null,
        "value": null
      },
      {
        "stage": "strategy",
        "name": "predicted_return_threshold",
        "passed": false,
        "detail": null,
        "value": null
      },
      {
        "stage": "strategy",
        "name": "qlib_signal_gating",
        "passed": true,
        "detail": null,
        "value": null
      },
      {
        "stage": "strategy",
        "name": "spread_filter",
        "passed": true,
        "detail": null,
        "value": null
      },
      {
        "stage": "strategy",
        "name": "vwap_relationship",
        "passed": false,
        "detail": null,
        "value": null
      }
    ],
    "final_decision_status": "rejected",
    "final_rejection_reason_code": "target_return_below_threshold",
    "final_rejection_reason_detail": "predicted_return_threshold",
    "notes": []
  },
  {
    "event_id": "cd699457-6846-4b2f-87f5-d6d4e0719bd3",
    "session_id": "00a83c2f-a276-413c-8e59-4e3f9f49726b",
    "run_id": "430562ad-46d6-47d4-b61b-1ab4d610b826",
    "correlation_id": "a99204b6-fb2b-450c-8152-94899884ea0d",
    "timestamp": "2026-03-23T19:59:00Z",
    "strategy": "scalping",
    "strategy_version": "v2",
    "mode": "paper",
    "broker_mode": "alpaca_paper_api",
    "symbol": "QBTS",
    "side_considered": "buy",
    "bracket_considered": false,
    "signal_source": "qlib_candidate_only",
    "qlib_raw_score": 0.002016462325409594,
    "predicted_return": 0.002016462325409594,
    "target_return": 0.002016462325409594,
    "candidate_rank": 2,
    "prediction_artifact_path": "C:\\Users\\User\\Documents\\MyTradingBot_Next\\models\\predictions\\latest.json",
    "model_artifact_path": "C:\\Users\\User\\Documents\\MyTradingBot_Next\\models\\qlib\\model.pkl",
    "dataset_artifact_path": "C:\\Users\\User\\Documents\\MyTradingBot_Next\\data\\qlib\\dataset.parquet",
    "source_data_timestamp": "2026-03-23T19:59:00Z",
    "source_data_freshness_minutes": 0,
    "rule_checks": [
      {
        "stage": "freshness",
        "name": "predictions_fresh",
        "passed": true,
        "detail": null,
        "value": null
      },
      {
        "stage": "freshness",
        "name": "market_snapshot_fresh",
        "passed": true,
        "detail": null,
        "value": null
      },
      {
        "stage": "strategy",
        "name": "duplicate_position_check",
        "passed": true,
        "detail": null,
        "value": null
      },
      {
        "stage": "strategy",
        "name": "foreign_position_check",
        "passed": true,
        "detail": null,
        "value": null
      },
      {
        "stage": "strategy",
        "name": "cooldown_check",
        "passed": true,
        "detail": null,
        "value": null
      },
      {
        "stage": "strategy",
        "name": "confidence_threshold",
        "passed": false,
        "detail": null,
        "value": null
      },
      {
        "stage": "strategy",
        "name": "cooldown_logic",
        "passed": true,
        "detail": null,
        "value": null
      },
      {
        "stage": "strategy",
        "name": "duplicate_position",
        "passed": true,
        "detail": null,
        "value": null
      },
      {
        "stage": "strategy",
        "name": "flatten_near_close_logic",
        "passed": true,
        "detail": null,
        "value": null
      },
      {
        "stage": "strategy",
        "name": "intraday_volatility_regime",
        "passed": true,
        "detail": null,
        "value": null
      },
      {
        "stage": "strategy",
        "name": "liquidity_filter",
        "passed": true,
        "detail": null,
        "value": null
      },
      {
        "stage": "strategy",
        "name": "liquidity_stress_filter",
        "passed": true,
        "detail": null,
        "value": null
      },
      {
        "stage": "strategy",
        "name": "liquidity_sweep_detection",
        "passed": false,
        "detail": null,
        "value": null
      },
      {
        "stage": "strategy",
        "name": "order_book_imbalance",
        "passed": false,
        "detail": null,
        "value": null
      },
      {
        "stage": "strategy",
        "name": "predicted_return_threshold",
        "passed": false,
        "detail": null,
        "value": null
      },
      {
        "stage": "strategy",
        "name": "qlib_signal_gating",
        "passed": true,
        "detail": null,
        "value": null
      },
      {
        "stage": "strategy",
        "name": "spread_filter",
        "passed": false,
        "detail": null,
        "value": null
      },
      {
        "stage": "strategy",
        "name": "vwap_relationship",
        "passed": false,
        "detail": null,
        "value": null
      }
    ],
    "final_decision_status": "rejected",
    "final_rejection_reason_code": "target_return_below_threshold",
    "final_rejection_reason_detail": "predicted_return_threshold",
    "notes": []
  },
  {
    "event_id": "80d3145c-36a7-4fbd-86e6-466921cfc357",
    "session_id": "00a83c2f-a276-413c-8e59-4e3f9f49726b",
    "run_id": "430562ad-46d6-47d4-b61b-1ab4d610b826",
    "correlation_id": "1cf144d1-026f-451f-b7c8-f1bce24d2f8e",
    "timestamp": "2026-03-23T19:59:00Z",
    "strategy": "scalping",
    "strategy_version": "v2",
    "mode": "paper",
    "broker_mode": "alpaca_paper_api",
    "symbol": "CRGY",
    "side_considered": "buy",
    "bracket_considered": false,
    "signal_source": "qlib_candidate_only",
    "qlib_raw_score": 0.001204714168005238,
    "predicted_return": 0.001204714168005238,
    "target_return": 0.001204714168005238,
    "candidate_rank": 3,
    "prediction_artifact_path": "C:\\Users\\User\\Documents\\MyTradingBot_Next\\models\\predictions\\latest.json",
    "model_artifact_path": "C:\\Users\\User\\Documents\\MyTradingBot_Next\\models\\qlib\\model.pkl",
    "dataset_artifact_path": "C:\\Users\\User\\Documents\\MyTradingBot_Next\\data\\qlib\\dataset.parquet",
    "source_data_timestamp": "2026-03-23T19:59:00Z",
    "source_data_freshness_minutes": 0,
    "rule_checks": [
      {
        "stage": "freshness",
        "name": "predictions_fresh",
        "passed": true,
        "detail": null,
        "value": null
      },
      {
        "stage": "freshness",
        "name": "market_snapshot_fresh",
        "passed": true,
        "detail": null,
        "value": null
      },
      {
        "stage": "strategy",
        "name": "duplicate_position_check",
        "passed": true,
        "detail": null,
        "value": null
      },
      {
        "stage": "strategy",
        "name": "foreign_position_check",
        "passed": true,
        "detail": null,
        "value": null
      },
      {
        "stage": "strategy",
        "name": "cooldown_check",
        "passed": true,
        "detail": null,
        "value": null
      },
      {
        "stage": "strategy",
        "name": "confidence_threshold",
        "passed": false,
        "detail": null,
        "value": null
      },
      {
        "stage": "strategy",
        "name": "cooldown_logic",
        "passed": true,
        "detail": null,
        "value": null
      },
      {
        "stage": "strategy",
        "name": "duplicate_position",
        "passed": true,
        "detail": null,
        "value": null
      },
      {
        "stage": "strategy",
        "name": "flatten_near_close_logic",
        "passed": true,
        "detail": null,
        "value": null
      },
      {
        "stage": "strategy",
        "name": "intraday_volatility_regime",
        "passed": true,
        "detail": null,
        "value": null
      },
      {
        "stage": "strategy",
        "name": "liquidity_filter",
        "passed": true,
        "detail": null,
        "value": null
      },
      {
        "stage": "strategy",
        "name": "liquidity_stress_filter",
        "passed": true,
        "detail": null,
        "value": null
      },
      {
        "stage": "strategy",
        "name": "liquidity_sweep_detection",
        "passed": true,
        "detail": null,
        "value": null
      },
      {
        "stage": "strategy",
        "name": "order_book_imbalance",
        "passed": false,
        "detail": null,
        "value": null
      },
      {
        "stage": "strategy",
        "name": "predicted_return_threshold",
        "passed": false,
        "detail": null,
        "value": null
      },
      {
        "stage": "strategy",
        "name": "qlib_signal_gating",
        "passed": true,
        "detail": null,
        "value": null
      },
      {
        "stage": "strategy",
        "name": "spread_filter",
        "passed": true,
        "detail": null,
        "value": null
      },
      {
        "stage": "strategy",
        "name": "vwap_relationship",
        "passed": false,
        "detail": null,
        "value": null
      }
    ],
    "final_decision_status": "rejected",
    "final_rejection_reason_code": "target_return_below_threshold",
    "final_rejection_reason_detail": "predicted_return_threshold",
    "notes": []
  },
  {
    "event_id": "9bfda871-2403-4aac-9011-5e7a719262d6",
    "session_id": "00a83c2f-a276-413c-8e59-4e3f9f49726b",
    "run_id": "430562ad-46d6-47d4-b61b-1ab4d610b826",
    "correlation_id": "1735b6cd-e991-4063-a883-f52ede103141",
    "timestamp": "2026-03-23T19:59:00Z",
    "strategy": "scalping",
    "strategy_version": "v2",
    "mode": "paper",
    "broker_mode": "alpaca_paper_api",
    "symbol": "XP",
    "side_considered": "buy",
    "bracket_considered": false,
    "signal_source": "qlib_candidate_only",
    "qlib_raw_score": 0.0005170294231273818,
    "predicted_return": 0.0005170294231273818,
    "target_return": 0.0005170294231273818,
    "candidate_rank": 4,
    "prediction_artifact_path": "C:\\Users\\User\\Documents\\MyTradingBot_Next\\models\\predictions\\latest.json",
    "model_artifact_path": "C:\\Users\\User\\Documents\\MyTradingBot_Next\\models\\qlib\\model.pkl",
    "dataset_artifact_path": "C:\\Users\\User\\Documents\\MyTradingBot_Next\\data\\qlib\\dataset.parquet",
    "source_data_timestamp": "2026-03-23T19:59:00Z",
    "source_data_freshness_minutes": 0,
    "rule_checks": [
      {
        "stage": "freshness",
        "name": "predictions_fresh",
        "passed": true,
        "detail": null,
        "value": null
      },
      {
        "stage": "freshness",
        "name": "market_snapshot_fresh",
        "passed": true,
        "detail": null,
        "value": null
      },
      {
        "stage": "strategy",
        "name": "duplicate_position_check",
        "passed": true,
        "detail": null,
        "value": null
      },
      {
        "stage": "strategy",
        "name": "foreign_position_check",
        "passed": true,
        "detail": null,
        "value": null
      },
      {
        "stage": "strategy",
        "name": "cooldown_check",
        "passed": true,
        "detail": null,
        "value": null
      },
      {
        "stage": "strategy",
        "name": "confidence_threshold",
        "passed": false,
        "detail": null,
        "value": null
      },
      {
        "stage": "strategy",
        "name": "cooldown_logic",
        "passed": true,
        "detail": null,
        "value": null
      },
      {
        "stage": "strategy",
        "name": "duplicate_position",
        "passed": true,
        "detail": null,
        "value": null
      },
      {
        "stage": "strategy",
        "name": "flatten_near_close_logic",
        "passed": true,
        "detail": null,
        "value": null
      },
      {
        "stage": "strategy",
        "name": "intraday_volatility_regime",
        "passed": true,
        "detail": null,
        "value": null
      },
      {
        "stage": "strategy",
        "name": "liquidity_filter",
        "passed": true,
        "detail": null,
        "value": null
      },
      {
        "stage": "strategy",
        "name": "liquidity_stress_filter",
        "passed": true,
        "detail": null,
        "value": null
      },
      {
        "stage": "strategy",
        "name": "liquidity_sweep_detection",
        "passed": true,
        "detail": null,
        "value": null
      },
      {
        "stage": "strategy",
        "name": "order_book_imbalance",
        "passed": true,
        "detail": null,
        "value": null
      },
      {
        "stage": "strategy",
        "name": "predicted_return_threshold",
        "passed": false,
        "detail": null,
        "value": null
      },
      {
        "stage": "strategy",
        "name": "qlib_signal_gating",
        "passed": true,
        "detail": null,
        "value": null
      },
      {
        "stage": "strategy",
        "name": "spread_filter",
        "passed": true,
        "detail": null,
        "value": null
      },
      {
        "stage": "strategy",
        "name": "vwap_relationship",
        "passed": true,
        "detail": null,
        "value": null
      }
    ],
    "final_decision_status": "rejected",
    "final_rejection_reason_code": "target_return_below_threshold",
    "final_rejection_reason_detail": "predicted_return_threshold",
    "notes": []
  },
  {
    "event_id": "4c8d83e9-acf0-4dda-b29f-b4e08c994693",
    "session_id": "00a83c2f-a276-413c-8e59-4e3f9f49726b",
    "run_id": "430562ad-46d6-47d4-b61b-1ab4d610b826",
    "correlation_id": "439cf13c-9a7c-4aed-b367-cdf4a471006c",
    "timestamp": "2026-03-23T19:59:00Z",
    "strategy": "scalping",
    "strategy_version": "v2",
    "mode": "paper",
    "broker_mode": "alpaca_paper_api",
    "symbol": "INFY",
    "side_considered": "buy",
    "bracket_considered": false,
    "signal_source": "qlib_candidate_only",
    "qlib_raw_score": 0.0004737092479869199,
    "predicted_return": 0.0004737092479869199,
    "target_return": 0.0004737092479869199,
    "candidate_rank": 5,
    "prediction_artifact_path": "C:\\Users\\User\\Documents\\MyTradingBot_Next\\models\\predictions\\latest.json",
    "model_artifact_path": "C:\\Users\\User\\Documents\\MyTradingBot_Next\\models\\qlib\\model.pkl",
    "dataset_artifact_path": "C:\\Users\\User\\Documents\\MyTradingBot_Next\\data\\qlib\\dataset.parquet",
    "source_data_timestamp": "2026-03-23T19:59:00Z",
    "source_data_freshness_minutes": 0,
    "rule_checks": [
      {
        "stage": "freshness",
        "name": "predictions_fresh",
        "passed": true,
        "detail": null,
        "value": null
      },
      {
        "stage": "freshness",
        "name": "market_snapshot_fresh",
        "passed": true,
        "detail": null,
        "value": null
      },
      {
        "stage": "strategy",
        "name": "duplicate_position_check",
        "passed": true,
        "detail": null,
        "value": null
      },
      {
        "stage": "strategy",
        "name": "foreign_position_check",
        "passed": true,
        "detail": null,
        "value": null
      },
      {
        "stage": "strategy",
        "name": "cooldown_check",
        "passed": true,
        "detail": null,
        "value": null
      },
      {
        "stage": "strategy",
        "name": "confidence_threshold",
        "passed": false,
        "detail": null,
        "value": null
      },
      {
        "stage": "strategy",
        "name": "cooldown_logic",
        "passed": true,
        "detail": null,
        "value": null
      },
      {
        "stage": "strategy",
        "name": "duplicate_position",
        "passed": true,
        "detail": null,
        "value": null
      },
      {
        "stage": "strategy",
        "name": "flatten_near_close_logic",
        "passed": true,
        "detail": null,
        "value": null
      },
      {
        "stage": "strategy",
        "name": "intraday_volatility_regime",
        "passed": true,
        "detail": null,
        "value": null
      },
      {
        "stage": "strategy",
        "name": "liquidity_filter",
        "passed": true,
        "detail": null,
        "value": null
      },
      {
        "stage": "strategy",
        "name": "liquidity_stress_filter",
        "passed": true,
        "detail": null,
        "value": null
      },
      {
        "stage": "strategy",
        "name": "liquidity_sweep_detection",
        "passed": true,
        "detail": null,
        "value": null
      },
      {
        "stage": "strategy",
        "name": "order_book_imbalance",
        "passed": true,
        "detail": null,
        "value": null
      },
      {
        "stage": "strategy",
        "name": "predicted_return_threshold",
        "passed": false,
        "detail": null,
        "value": null
      },
      {
        "stage": "strategy",
        "name": "qlib_signal_gating",
        "passed": true,
        "detail": null,
        "value": null
      },
      {
        "stage": "strategy",
        "name": "spread_filter",
        "passed": false,
        "detail": null,
        "value": null
      },
      {
        "stage": "strategy",
        "name": "vwap_relationship",
        "passed": true,
        "detail": null,
        "value": null
      }
    ],
    "final_decision_status": "rejected",
    "final_rejection_reason_code": "target_return_below_threshold",
    "final_rejection_reason_detail": "predicted_return_threshold",
    "notes": []
  },
  {
    "event_id": "2770e321-7e50-44c8-848a-6da4eb85d71f",
    "session_id": "00a83c2f-a276-413c-8e59-4e3f9f49726b",
    "run_id": "430562ad-46d6-47d4-b61b-1ab4d610b826",
    "correlation_id": "4c6314fa-aa8f-4861-975e-b9e8c4602d10",
    "timestamp": "2026-03-23T19:59:00Z",
    "strategy": "scalping",
    "strategy_version": "v2",
    "mode": "paper",
    "broker_mode": "alpaca_paper_api",
    "symbol": "SAN",
    "side_considered": "buy",
    "bracket_considered": false,
    "signal_source": "qlib_candidate_only",
    "qlib_raw_score": 0.0004212788493466776,
    "predicted_return": 0.0004212788493466776,
    "target_return": 0.0004212788493466776,
    "candidate_rank": 6,
    "prediction_artifact_path": "C:\\Users\\User\\Documents\\MyTradingBot_Next\\models\\predictions\\latest.json",
    "model_artifact_path": "C:\\Users\\User\\Documents\\MyTradingBot_Next\\models\\qlib\\model.pkl",
    "dataset_artifact_path": "C:\\Users\\User\\Documents\\MyTradingBot_Next\\data\\qlib\\dataset.parquet",
    "source_data_timestamp": "2026-03-23T19:59:00Z",
    "source_data_freshness_minutes": 0,
    "rule_checks": [
      {
        "stage": "freshness",
        "name": "predictions_fresh",
        "passed": true,
        "detail": null,
        "value": null
      },
      {
        "stage": "freshness",
        "name": "market_snapshot_fresh",
        "passed": true,
        "detail": null,
        "value": null
      },
      {
        "stage": "strategy",
        "name": "duplicate_position_check",
        "passed": true,
        "detail": null,
        "value": null
      },
      {
        "stage": "strategy",
        "name": "foreign_position_check",
        "passed": true,
        "detail": null,
        "value": null
      },
      {
        "stage": "strategy",
        "name": "cooldown_check",
        "passed": true,
        "detail": null,
        "value": null
      },
      {
        "stage": "strategy",
        "name": "confidence_threshold",
        "passed": false,
        "detail": null,
        "value": null
      },
      {
        "stage": "strategy",
        "name": "cooldown_logic",
        "passed": true,
        "detail": null,
        "value": null
      },
      {
        "stage": "strategy",
        "name": "duplicate_position",
        "passed": true,
        "detail": null,
        "value": null
      },
      {
        "stage": "strategy",
        "name": "flatten_near_close_logic",
        "passed": true,
        "detail": null,
        "value": null
      },
      {
        "stage": "strategy",
        "name": "intraday_volatility_regime",
        "passed": true,
        "detail": null,
        "value": null
      },
      {
        "stage": "strategy",
        "name": "liquidity_filter",
        "passed": true,
        "detail": null,
        "value": null
      },
      {
        "stage": "strategy",
        "name": "liquidity_stress_filter",
        "passed": true,
        "detail": null,
        "value": null
      },
      {
        "stage": "strategy",
        "name": "liquidity_sweep_detection",
        "passed": true,
        "detail": null,
        "value": null
      },
      {
        "stage": "strategy",
        "name": "order_book_imbalance",
        "passed": false,
        "detail": null,
        "value": null
      },
      {
        "stage": "strategy",
        "name": "predicted_return_threshold",
        "passed": false,
        "detail": null,
        "value": null
      },
      {
        "stage": "strategy",
        "name": "qlib_signal_gating",
        "passed": true,
        "detail": null,
        "value": null
      },
      {
        "stage": "strategy",
        "name": "spread_filter",
        "passed": true,
        "detail": null,
        "value": null
      },
      {
        "stage": "strategy",
        "name": "vwap_relationship",
        "passed": false,
        "detail": null,
        "value": null
      }
    ],
    "final_decision_status": "rejected",
    "final_rejection_reason_code": "target_return_below_threshold",
    "final_rejection_reason_detail": "predicted_return_threshold",
    "notes": []
  },
  {
    "event_id": "8dfa6b94-ea05-4cf2-82b3-81962a91a989",
    "session_id": "00a83c2f-a276-413c-8e59-4e3f9f49726b",
    "run_id": "430562ad-46d6-47d4-b61b-1ab4d610b826",
    "correlation_id": "8ed969aa-24c8-4951-8300-277a992cacd2",
    "timestamp": "2026-03-23T19:59:00Z",
    "strategy": "scalping",
    "strategy_version": "v2",
    "mode": "paper",
    "broker_mode": "alpaca_paper_api",
    "symbol": "SMR",
    "side_considered": "buy",
    "bracket_considered": false,
    "signal_source": "qlib_candidate_only",
    "qlib_raw_score": 0.00031197624926612033,
    "predicted_return": 0.00031197624926612033,
    "target_return": 0.00031197624926612033,
    "candidate_rank": 7,
    "prediction_artifact_path": "C:\\Users\\User\\Documents\\MyTradingBot_Next\\models\\predictions\\latest.json",
    "model_artifact_path": "C:\\Users\\User\\Documents\\MyTradingBot_Next\\models\\qlib\\model.pkl",
    "dataset_artifact_path": "C:\\Users\\User\\Documents\\MyTradingBot_Next\\data\\qlib\\dataset.parquet",
    "source_data_timestamp": "2026-03-23T19:59:00Z",
    "source_data_freshness_minutes": 0,
    "rule_checks": [
      {
        "stage": "freshness",
        "name": "predictions_fresh",
        "passed": true,
        "detail": null,
        "value": null
      },
      {
        "stage": "freshness",
        "name": "market_snapshot_fresh",
        "passed": true,
        "detail": null,
        "value": null
      },
      {
        "stage": "strategy",
        "name": "duplicate_position_check",
        "passed": true,
        "detail": null,
        "value": null
      },
      {
        "stage": "strategy",
        "name": "foreign_position_check",
        "passed": true,
        "detail": null,
        "value": null
      },
      {
        "stage": "strategy",
        "name": "cooldown_check",
        "passed": true,
        "detail": null,
        "value": null
      },
      {
        "stage": "strategy",
        "name": "confidence_threshold",
        "passed": false,
        "detail": null,
        "value": null
      },
      {
        "stage": "strategy",
        "name": "cooldown_logic",
        "passed": true,
        "detail": null,
        "value": null
      },
      {
        "stage": "strategy",
        "name": "duplicate_position",
        "passed": true,
        "detail": null,
        "value": null
      },
      {
        "stage": "strategy",
        "name": "flatten_near_close_logic",
        "passed": true,
        "detail": null,
        "value": null
      },
      {
        "stage": "strategy",
        "name": "intraday_volatility_regime",
        "passed": true,
        "detail": null,
        "value": null
      },
      {
        "stage": "strategy",
        "name": "liquidity_filter",
        "passed": true,
        "detail": null,
        "value": null
      },
      {
        "stage": "strategy",
        "name": "liquidity_stress_filter",
        "passed": true,
        "detail": null,
        "value": null
      },
      {
        "stage": "strategy",
        "name": "liquidity_sweep_detection",
        "passed": true,
        "detail": null,
        "value": null
      },
      {
        "stage": "strategy",
        "name": "order_book_imbalance",
        "passed": false,
        "detail": null,
        "value": null
      },
      {
        "stage": "strategy",
        "name": "predicted_return_threshold",
        "passed": false,
        "detail": null,
        "value": null
      },
      {
        "stage": "strategy",
        "name": "qlib_signal_gating",
        "passed": true,
        "detail": null,
        "value": null
      },
      {
        "stage": "strategy",
        "name": "spread_filter",
        "passed": false,
        "detail": null,
        "value": null
      },
      {
        "stage": "strategy",
        "name": "vwap_relationship",
        "passed": false,
        "detail": null,
        "value": null
      }
    ],
    "final_decision_status": "rejected",
    "final_rejection_reason_code": "target_return_below_threshold",
    "final_rejection_reason_detail": "predicted_return_threshold",
    "notes": []
  },
  {
    "event_id": "d239f2bf-c2fd-46ab-99b8-40688617e899",
    "session_id": "00a83c2f-a276-413c-8e59-4e3f9f49726b",
    "run_id": "430562ad-46d6-47d4-b61b-1ab4d610b826",
    "correlation_id": "01d8c31e-87f8-4ade-9060-0e77f03bc1fe",
    "timestamp": "2026-03-23T19:59:00Z",
    "strategy": "scalping",
    "strategy_version": "v2",
    "mode": "paper",
    "broker_mode": "alpaca_paper_api",
    "symbol": "VTRS",
    "side_considered": "buy",
    "bracket_considered": false,
    "signal_source": "qlib_candidate_only",
    "qlib_raw_score": 0.00027674155746258727,
    "predicted_return": 0.00027674155746258727,
    "target_return": 0.00027674155746258727,
    "candidate_rank": 8,
    "prediction_artifact_path": "C:\\Users\\User\\Documents\\MyTradingBot_Next\\models\\predictions\\latest.json",
    "model_artifact_path": "C:\\Users\\User\\Documents\\MyTradingBot_Next\\models\\qlib\\model.pkl",
    "dataset_artifact_path": "C:\\Users\\User\\Documents\\MyTradingBot_Next\\data\\qlib\\dataset.parquet",
    "source_data_timestamp": "2026-03-23T19:59:00Z",
    "source_data_freshness_minutes": 0,
    "rule_checks": [
      {
        "stage": "freshness",
        "name": "predictions_fresh",
        "passed": true,
        "detail": null,
        "value": null
      },
      {
        "stage": "freshness",
        "name": "market_snapshot_fresh",
        "passed": true,
        "detail": null,
        "value": null
      },
      {
        "stage": "strategy",
        "name": "duplicate_position_check",
        "passed": true,
        "detail": null,
        "value": null
      },
      {
        "stage": "strategy",
        "name": "foreign_position_check",
        "passed": true,
        "detail": null,
        "value": null
      },
      {
        "stage": "strategy",
        "name": "cooldown_check",
        "passed": true,
        "detail": null,
        "value": null
      },
      {
        "stage": "strategy",
        "name": "confidence_threshold",
        "passed": false,
        "detail": null,
        "value": null
      },
      {
        "stage": "strategy",
        "name": "cooldown_logic",
        "passed": true,
        "detail": null,
        "value": null
      },
      {
        "stage": "strategy",
        "name": "duplicate_position",
        "passed": true,
        "detail": null,
        "value": null
      },
      {
        "stage": "strategy",
        "name": "flatten_near_close_logic",
        "passed": true,
        "detail": null,
        "value": null
      },
      {
        "stage": "strategy",
        "name": "intraday_volatility_regime",
        "passed": true,
        "detail": null,
        "value": null
      },
      {
        "stage": "strategy",
        "name": "liquidity_filter",
        "passed": true,
        "detail": null,
        "value": null
      },
      {
        "stage": "strategy",
        "name": "liquidity_stress_filter",
        "passed": true,
        "detail": null,
        "value": null
      },
      {
        "stage": "strategy",
        "name": "liquidity_sweep_detection",
        "passed": true,
        "detail": null,
        "value": null
      },
      {
        "stage": "strategy",
        "name": "order_book_imbalance",
        "passed": false,
        "detail": null,
        "value": null
      },
      {
        "stage": "strategy",
        "name": "predicted_return_threshold",
        "passed": false,
        "detail": null,
        "value": null
      },
      {
        "stage": "strategy",
        "name": "qlib_signal_gating",
        "passed": true,
        "detail": null,
        "value": null
      },
      {
        "stage": "strategy",
        "name": "spread_filter",
        "passed": true,
        "detail": null,
        "value": null
      },
      {
        "stage": "strategy",
        "name": "vwap_relationship",
        "passed": false,
        "detail": null,
        "value": null
      }
    ],
    "final_decision_status": "rejected",
    "final_rejection_reason_code": "target_return_below_threshold",
    "final_rejection_reason_detail": "predicted_return_threshold",
    "notes": []
  },
  {
    "event_id": "39836e7a-5e8e-4565-8207-719af0eb7b84",
    "session_id": "00a83c2f-a276-413c-8e59-4e3f9f49726b",
    "run_id": "430562ad-46d6-47d4-b61b-1ab4d610b826",
    "correlation_id": "2a497dac-f8be-46b5-94f5-b68854758714",
    "timestamp": "2026-03-23T19:59:00Z",
    "strategy": "scalping",
    "strategy_version": "v2",
    "mode": "paper",
    "broker_mode": "alpaca_paper_api",
    "symbol": "PATH",
    "side_considered": "buy",
    "bracket_considered": false,
    "signal_source": "qlib_candidate_only",
    "qlib_raw_score": 0.00026771513298575985,
    "predicted_return": 0.00026771513298575985,
    "target_return": 0.00026771513298575985,
    "candidate_rank": 9,
    "prediction_artifact_path": "C:\\Users\\User\\Documents\\MyTradingBot_Next\\models\\predictions\\latest.json",
    "model_artifact_path": "C:\\Users\\User\\Documents\\MyTradingBot_Next\\models\\qlib\\model.pkl",
    "dataset_artifact_path": "C:\\Users\\User\\Documents\\MyTradingBot_Next\\data\\qlib\\dataset.parquet",
    "source_data_timestamp": "2026-03-23T19:59:00Z",
    "source_data_freshness_minutes": 0,
    "rule_checks": [
      {
        "stage": "freshness",
        "name": "predictions_fresh",
        "passed": true,
        "detail": null,
        "value": null
      },
      {
        "stage": "freshness",
        "name": "market_snapshot_fresh",
        "passed": true,
        "detail": null,
        "value": null
      },
      {
        "stage": "strategy",
        "name": "duplicate_position_check",
        "passed": true,
        "detail": null,
        "value": null
      },
      {
        "stage": "strategy",
        "name": "foreign_position_check",
        "passed": true,
        "detail": null,
        "value": null
      },
      {
        "stage": "strategy",
        "name": "cooldown_check",
        "passed": true,
        "detail": null,
        "value": null
      },
      {
        "stage": "strategy",
        "name": "confidence_threshold",
        "passed": false,
        "detail": null,
        "value": null
      },
      {
        "stage": "strategy",
        "name": "cooldown_logic",
        "passed": true,
        "detail": null,
        "value": null
      },
      {
        "stage": "strategy",
        "name": "duplicate_position",
        "passed": true,
        "detail": null,
        "value": null
      },
      {
        "stage": "strategy",
        "name": "flatten_near_close_logic",
        "passed": true,
        "detail": null,
        "value": null
      },
      {
        "stage": "strategy",
        "name": "intraday_volatility_regime",
        "passed": true,
        "detail": null,
        "value": null
      },
      {
        "stage": "strategy",
        "name": "liquidity_filter",
        "passed": true,
        "detail": null,
        "value": null
      },
      {
        "stage": "strategy",
        "name": "liquidity_stress_filter",
        "passed": true,
        "detail": null,
        "value": null
      },
      {
        "stage": "strategy",
        "name": "liquidity_sweep_detection",
        "passed": true,
        "detail": null,
        "value": null
      },
      {
        "stage": "strategy",
        "name": "order_book_imbalance",
        "passed": true,
        "detail": null,
        "value": null
      },
      {
        "stage": "strategy",
        "name": "predicted_return_threshold",
        "passed": false,
        "detail": null,
        "value": null
      },
      {
        "stage": "strategy",
        "name": "qlib_signal_gating",
        "passed": true,
        "detail": null,
        "value": null
      },
      {
        "stage": "strategy",
        "name": "spread_filter",
        "passed": false,
        "detail": null,
        "value": null
      },
      {
        "stage": "strategy",
        "name": "vwap_relationship",
        "passed": true,
        "detail": null,
        "value": null
      }
    ],
    "final_decision_status": "rejected",
    "final_rejection_reason_code": "target_return_below_threshold",
    "final_rejection_reason_detail": "predicted_return_threshold",
    "notes": []
  },
  {
    "event_id": "aff2247b-9857-4e77-a99b-6c4434b21648",
    "session_id": "00a83c2f-a276-413c-8e59-4e3f9f49726b",
    "run_id": "430562ad-46d6-47d4-b61b-1ab4d610b826",
    "correlation_id": "69ee6304-29ac-4daa-a502-8f3af06d379b",
    "timestamp": "2026-03-23T19:59:00Z",
    "strategy": "scalping",
    "strategy_version": "v2",
    "mode": "paper",
    "broker_mode": "alpaca_paper_api",
    "symbol": "DKNG",
    "side_considered": "buy",
    "bracket_considered": false,
    "signal_source": "qlib_candidate_only",
    "qlib_raw_score": 0.00026428963875322026,
    "predicted_return": 0.00026428963875322026,
    "target_return": 0.00026428963875322026,
    "candidate_rank": 10,
    "prediction_artifact_path": "C:\\Users\\User\\Documents\\MyTradingBot_Next\\models\\predictions\\latest.json",
    "model_artifact_path": "C:\\Users\\User\\Documents\\MyTradingBot_Next\\models\\qlib\\model.pkl",
    "dataset_artifact_path": "C:\\Users\\User\\Documents\\MyTradingBot_Next\\data\\qlib\\dataset.parquet",
    "source_data_timestamp": "2026-03-23T19:59:00Z",
    "source_data_freshness_minutes": 0,
    "rule_checks": [
      {
        "stage": "freshness",
        "name": "predictions_fresh",
        "passed": true,
        "detail": null,
        "value": null
      },
      {
        "stage": "freshness",
        "name": "market_snapshot_fresh",
        "passed": true,
        "detail": null,
        "value": null
      },
      {
        "stage": "strategy",
        "name": "duplicate_position_check",
        "passed": true,
        "detail": null,
        "value": null
      },
      {
        "stage": "strategy",
        "name": "foreign_position_check",
        "passed": true,
        "detail": null,
        "value": null
      },
      {
        "stage": "strategy",
        "name": "cooldown_check",
        "passed": true,
        "detail": null,
        "value": null
      },
      {
        "stage": "strategy",
        "name": "confidence_threshold",
        "passed": false,
        "detail": null,
        "value": null
      },
      {
        "stage": "strategy",
        "name": "cooldown_logic",
        "passed": true,
        "detail": null,
        "value": null
      },
      {
        "stage": "strategy",
        "name": "duplicate_position",
        "passed": true,
        "detail": null,
        "value": null
      },
      {
        "stage": "strategy",
        "name": "flatten_near_close_logic",
        "passed": true,
        "detail": null,
        "value": null
      },
      {
        "stage": "strategy",
        "name": "intraday_volatility_regime",
        "passed": true,
        "detail": null,
        "value": null
      },
      {
        "stage": "strategy",
        "name": "liquidity_filter",
        "passed": true,
        "detail": null,
        "value": null
      },
      {
        "stage": "strategy",
        "name": "liquidity_stress_filter",
        "passed": true,
        "detail": null,
        "value": null
      },
      {
        "stage": "strategy",
        "name": "liquidity_sweep_detection",
        "passed": true,
        "detail": null,
        "value": null
      },
      {
        "stage": "strategy",
        "name": "order_book_imbalance",
        "passed": false,
        "detail": null,
        "value": null
      },
      {
        "stage": "strategy",
        "name": "predicted_return_threshold",
        "passed": false,
        "detail": null,
        "value": null
      },
      {
        "stage": "strategy",
        "name": "qlib_signal_gating",
        "passed": true,
        "detail": null,
        "value": null
      },
      {
        "stage": "strategy",
        "name": "spread_filter",
        "passed": false,
        "detail": null,
        "value": null
      },
      {
        "stage": "strategy",
        "name": "vwap_relationship",
        "passed": false,
        "detail": null,
        "value": null
      }
    ],
    "final_decision_status": "rejected",
    "final_rejection_reason_code": "target_return_below_threshold",
    "final_rejection_reason_detail": "predicted_return_threshold",
    "notes": []
  },
  {
    "event_id": "0dbae505-fa9a-4837-a8aa-6ca38dea13ed",
    "session_id": "00a83c2f-a276-413c-8e59-4e3f9f49726b",
    "run_id": "430562ad-46d6-47d4-b61b-1ab4d610b826",
    "correlation_id": "888c58d7-92fc-4aa5-a42f-6714e7af2d0a",
    "timestamp": "2026-03-23T19:59:00Z",
    "strategy": "scalping",
    "strategy_version": "v2",
    "mode": "paper",
    "broker_mode": "alpaca_paper_api",
    "symbol": "BAC",
    "side_considered": "buy",
    "bracket_considered": false,
    "signal_source": "qlib_candidate_only",
    "qlib_raw_score": 0.00022933777165574663,
    "predicted_return": 0.00022933777165574663,
    "target_return": 0.00022933777165574663,
    "candidate_rank": 11,
    "prediction_artifact_path": "C:\\Users\\User\\Documents\\MyTradingBot_Next\\models\\predictions\\latest.json",
    "model_artifact_path": "C:\\Users\\User\\Documents\\MyTradingBot_Next\\models\\qlib\\model.pkl",
    "dataset_artifact_path": "C:\\Users\\User\\Documents\\MyTradingBot_Next\\data\\qlib\\dataset.parquet",
    "source_data_timestamp": "2026-03-23T19:59:00Z",
    "source_data_freshness_minutes": 0,
    "rule_checks": [
      {
        "stage": "freshness",
        "name": "predictions_fresh",
        "passed": true,
        "detail": null,
        "value": null
      },
      {
        "stage": "freshness",
        "name": "market_snapshot_fresh",
        "passed": true,
        "detail": null,
        "value": null
      },
      {
        "stage": "strategy",
        "name": "duplicate_position_check",
        "passed": true,
        "detail": null,
        "value": null
      },
      {
        "stage": "strategy",
        "name": "foreign_position_check",
        "passed": true,
        "detail": null,
        "value": null
      },
      {
        "stage": "strategy",
        "name": "cooldown_check",
        "passed": true,
        "detail": null,
        "value": null
      },
      {
        "stage": "strategy",
        "name": "confidence_threshold",
        "passed": false,
        "detail": null,
        "value": null
      },
      {
        "stage": "strategy",
        "name": "cooldown_logic",
        "passed": true,
        "detail": null,
        "value": null
      },
      {
        "stage": "strategy",
        "name": "duplicate_position",
        "passed": true,
        "detail": null,
        "value": null
      },
      {
        "stage": "strategy",
        "name": "flatten_near_close_logic",
        "passed": true,
        "detail": null,
        "value": null
      },
      {
        "stage": "strategy",
        "name": "intraday_volatility_regime",
        "passed": true,
        "detail": null,
        "value": null
      },
      {
        "stage": "strategy",
        "name": "liquidity_filter",
        "passed": true,
        "detail": null,
        "value": null
      },
      {
        "stage": "strategy",
        "name": "liquidity_stress_filter",
        "passed": true,
        "detail": null,
        "value": null
      },
      {
        "stage": "strategy",
        "name": "liquidity_sweep_detection",
        "passed": true,
        "detail": null,
        "value": null
      },
      {
        "stage": "strategy",
        "name": "order_book_imbalance",
        "passed": true,
        "detail": null,
        "value": null
      },
      {
        "stage": "strategy",
        "name": "predicted_return_threshold",
        "passed": false,
        "detail": null,
        "value": null
      },
      {
        "stage": "strategy",
        "name": "qlib_signal_gating",
        "passed": true,
        "detail": null,
        "value": null
      },
      {
        "stage": "strategy",
        "name": "spread_filter",
        "passed": true,
        "detail": null,
        "value": null
      },
      {
        "stage": "strategy",
        "name": "vwap_relationship",
        "passed": true,
        "detail": null,
        "value": null
      }
    ],
    "final_decision_status": "rejected",
    "final_rejection_reason_code": "target_return_below_threshold",
    "final_rejection_reason_detail": "predicted_return_threshold",
    "notes": []
  },
  {
    "event_id": "e83aff48-906f-474b-a469-8bd392269735",
    "session_id": "00a83c2f-a276-413c-8e59-4e3f9f49726b",
    "run_id": "430562ad-46d6-47d4-b61b-1ab4d610b826",
    "correlation_id": "ca7f128b-a0f1-4b3d-8bbc-6d485b03c3e9",
    "timestamp": "2026-03-23T19:59:00Z",
    "strategy": "scalping",
    "strategy_version": "v2",
    "mode": "paper",
    "broker_mode": "alpaca_paper_api",
    "symbol": "SMCI",
    "side_considered": "buy",
    "bracket_considered": false,
    "signal_source": "qlib_candidate_only",
    "qlib_raw_score": 0.0002255830974823449,
    "predicted_return": 0.0002255830974823449,
    "target_return": 0.0002255830974823449,
    "candidate_rank": 12,
    "prediction_artifact_path": "C:\\Users\\User\\Documents\\MyTradingBot_Next\\models\\predictions\\latest.json",
    "model_artifact_path": "C:\\Users\\User\\Documents\\MyTradingBot_Next\\models\\qlib\\model.pkl",
    "dataset_artifact_path": "C:\\Users\\User\\Documents\\MyTradingBot_Next\\data\\qlib\\dataset.parquet",
    "source_data_timestamp": "2026-03-23T19:59:00Z",
    "source_data_freshness_minutes": 0,
    "rule_checks": [
      {
        "stage": "freshness",
        "name": "predictions_fresh",
        "passed": true,
        "detail": null,
        "value": null
      },
      {
        "stage": "freshness",
        "name": "market_snapshot_fresh",
        "passed": true,
        "detail": null,
        "value": null
      },
      {
        "stage": "strategy",
        "name": "duplicate_position_check",
        "passed": true,
        "detail": null,
        "value": null
      },
      {
        "stage": "strategy",
        "name": "foreign_position_check",
        "passed": true,
        "detail": null,
        "value": null
      },
      {
        "stage": "strategy",
        "name": "cooldown_check",
        "passed": true,
        "detail": null,
        "value": null
      },
      {
        "stage": "strategy",
        "name": "confidence_threshold",
        "passed": false,
        "detail": null,
        "value": null
      },
      {
        "stage": "strategy",
        "name": "cooldown_logic",
        "passed": true,
        "detail": null,
        "value": null
      },
      {
        "stage": "strategy",
        "name": "duplicate_position",
        "passed": true,
        "detail": null,
        "value": null
      },
      {
        "stage": "strategy",
        "name": "flatten_near_close_logic",
        "passed": true,
        "detail": null,
        "value": null
      },
      {
        "stage": "strategy",
        "name": "intraday_volatility_regime",
        "passed": true,
        "detail": null,
        "value": null
      },
      {
        "stage": "strategy",
        "name": "liquidity_filter",
        "passed": true,
        "detail": null,
        "value": null
      },
      {
        "stage": "strategy",
        "name": "liquidity_stress_filter",
        "passed": true,
        "detail": null,
        "value": null
      },
      {
        "stage": "strategy",
        "name": "liquidity_sweep_detection",
        "passed": true,
        "detail": null,
        "value": null
      },
      {
        "stage": "strategy",
        "name": "order_book_imbalance",
        "passed": false,
        "detail": null,
        "value": null
      },
      {
        "stage": "strategy",
        "name": "predicted_return_threshold",
        "passed": false,
        "detail": null,
        "value": null
      },
      {
        "stage": "strategy",
        "name": "qlib_signal_gating",
        "passed": true,
        "detail": null,
        "value": null
      },
      {
        "stage": "strategy",
        "name": "spread_filter",
        "passed": false,
        "detail": null,
        "value": null
      },
      {
        "stage": "strategy",
        "name": "vwap_relationship",
        "passed": false,
        "detail": null,
        "value": null
      }
    ],
    "final_decision_status": "rejected",
    "final_rejection_reason_code": "target_return_below_threshold",
    "final_rejection_reason_detail": "predicted_return_threshold",
    "notes": []
  },
  {
    "event_id": "1baaa852-5216-4655-9bc0-baf1936518ee",
    "session_id": "00a83c2f-a276-413c-8e59-4e3f9f49726b",
    "run_id": "430562ad-46d6-47d4-b61b-1ab4d610b826",
    "correlation_id": "d196820e-4cef-4d5f-9c6d-f90fb660ac37",
    "timestamp": "2026-03-23T19:59:00Z",
    "strategy": "scalping",
    "strategy_version": "v2",
    "mode": "paper",
    "broker_mode": "alpaca_paper_api",
    "symbol": "FIG",
    "side_considered": "buy",
    "bracket_considered": false,
    "signal_source": "qlib_candidate_only",
    "qlib_raw_score": 0.00022380846409068896,
    "predicted_return": 0.00022380846409068896,
    "target_return": 0.00022380846409068896,
    "candidate_rank": 13,
    "prediction_artifact_path": "C:\\Users\\User\\Documents\\MyTradingBot_Next\\models\\predictions\\latest.json",
    "model_artifact_path": "C:\\Users\\User\\Documents\\MyTradingBot_Next\\models\\qlib\\model.pkl",
    "dataset_artifact_path": "C:\\Users\\User\\Documents\\MyTradingBot_Next\\data\\qlib\\dataset.parquet",
    "source_data_timestamp": "2026-03-23T19:59:00Z",
    "source_data_freshness_minutes": 0,
    "rule_checks": [
      {
        "stage": "freshness",
        "name": "predictions_fresh",
        "passed": true,
        "detail": null,
        "value": null
      },
      {
        "stage": "freshness",
        "name": "market_snapshot_fresh",
        "passed": true,
        "detail": null,
        "value": null
      },
      {
        "stage": "strategy",
        "name": "duplicate_position_check",
        "passed": true,
        "detail": null,
        "value": null
      },
      {
        "stage": "strategy",
        "name": "foreign_position_check",
        "passed": true,
        "detail": null,
        "value": null
      },
      {
        "stage": "strategy",
        "name": "cooldown_check",
        "passed": true,
        "detail": null,
        "value": null
      },
      {
        "stage": "strategy",
        "name": "confidence_threshold",
        "passed": false,
        "detail": null,
        "value": null
      },
      {
        "stage": "strategy",
        "name": "cooldown_logic",
        "passed": true,
        "detail": null,
        "value": null
      },
      {
        "stage": "strategy",
        "name": "duplicate_position",
        "passed": true,
        "detail": null,
        "value": null
      },
      {
        "stage": "strategy",
        "name": "flatten_near_close_logic",
        "passed": true,
        "detail": null,
        "value": null
      },
      {
        "stage": "strategy",
        "name": "intraday_volatility_regime",
        "passed": true,
        "detail": null,
        "value": null
      },
      {
        "stage": "strategy",
        "name": "liquidity_filter",
        "passed": true,
        "detail": null,
        "value": null
      },
      {
        "stage": "strategy",
        "name": "liquidity_stress_filter",
        "passed": true,
        "detail": null,
        "value": null
      },
      {
        "stage": "strategy",
        "name": "liquidity_sweep_detection",
        "passed": true,
        "detail": null,
        "value": null
      },
      {
        "stage": "strategy",
        "name": "order_book_imbalance",
        "passed": false,
        "detail": null,
        "value": null
      },
      {
        "stage": "strategy",
        "name": "predicted_return_threshold",
        "passed": false,
        "detail": null,
        "value": null
      },
      {
        "stage": "strategy",
        "name": "qlib_signal_gating",
        "passed": true,
        "detail": null,
        "value": null
      },
      {
        "stage": "strategy",
        "name": "spread_filter",
        "passed": false,
        "detail": null,
        "value": null
      },
      {
        "stage": "strategy",
        "name": "vwap_relationship",
        "passed": false,
        "detail": null,
        "value": null
      }
    ],
    "final_decision_status": "rejected",
    "final_rejection_reason_code": "target_return_below_threshold",
    "final_rejection_reason_detail": "predicted_return_threshold",
    "notes": []
  },
  {
    "event_id": "dc6a1f4b-20f9-4e8b-ba68-51f9d68a575b",
    "session_id": "00a83c2f-a276-413c-8e59-4e3f9f49726b",
    "run_id": "430562ad-46d6-47d4-b61b-1ab4d610b826",
    "correlation_id": "fb0b61df-efc7-410b-a9c8-57c53f754e53",
    "timestamp": "2026-03-23T19:59:00Z",
    "strategy": "scalping",
    "strategy_version": "v2",
    "mode": "paper",
    "broker_mode": "alpaca_paper_api",
    "symbol": "BAX",
    "side_considered": "buy",
    "bracket_considered": false,
    "signal_source": "qlib_candidate_only",
    "qlib_raw_score": 0.00022342920201843435,
    "predicted_return": 0.00022342920201843435,
    "target_return": 0.00022342920201843435,
    "candidate_rank": 14,
    "prediction_artifact_path": "C:\\Users\\User\\Documents\\MyTradingBot_Next\\models\\predictions\\latest.json",
    "model_artifact_path": "C:\\Users\\User\\Documents\\MyTradingBot_Next\\models\\qlib\\model.pkl",
    "dataset_artifact_path": "C:\\Users\\User\\Documents\\MyTradingBot_Next\\data\\qlib\\dataset.parquet",
    "source_data_timestamp": "2026-03-23T19:59:00Z",
    "source_data_freshness_minutes": 0,
    "rule_checks": [
      {
        "stage": "freshness",
        "name": "predictions_fresh",
        "passed": true,
        "detail": null,
        "value": null
      },
      {
        "stage": "freshness",
        "name": "market_snapshot_fresh",
        "passed": true,
        "detail": null,
        "value": null
      },
      {
        "stage": "strategy",
        "name": "duplicate_position_check",
        "passed": true,
        "detail": null,
        "value": null
      },
      {
        "stage": "strategy",
        "name": "foreign_position_check",
        "passed": true,
        "detail": null,
        "value": null
      },
      {
        "stage": "strategy",
        "name": "cooldown_check",
        "passed": true,
        "detail": null,
        "value": null
      },
      {
        "stage": "strategy",
        "name": "confidence_threshold",
        "passed": false,
        "detail": null,
        "value": null
      },
      {
        "stage": "strategy",
        "name": "cooldown_logic",
        "passed": true,
        "detail": null,
        "value": null
      },
      {
        "stage": "strategy",
        "name": "duplicate_position",
        "passed": true,
        "detail": null,
        "value": null
      },
      {
        "stage": "strategy",
        "name": "flatten_near_close_logic",
        "passed": true,
        "detail": null,
        "value": null
      },
      {
        "stage": "strategy",
        "name": "intraday_volatility_regime",
        "passed": true,
        "detail": null,
        "value": null
      },
      {
        "stage": "strategy",
        "name": "liquidity_filter",
        "passed": true,
        "detail": null,
        "value": null
      },
      {
        "stage": "strategy",
        "name": "liquidity_stress_filter",
        "passed": true,
        "detail": null,
        "value": null
      },
      {
        "stage": "strategy",
        "name": "liquidity_sweep_detection",
        "passed": true,
        "detail": null,
        "value": null
      },
      {
        "stage": "strategy",
        "name": "order_book_imbalance",
        "passed": false,
        "detail": null,
        "value": null
      },
      {
        "stage": "strategy",
        "name": "predicted_return_threshold",
        "passed": false,
        "detail": null,
        "value": null
      },
      {
        "stage": "strategy",
        "name": "qlib_signal_gating",
        "passed": true,
        "detail": null,
        "value": null
      },
      {
        "stage": "strategy",
        "name": "spread_filter",
        "passed": true,
        "detail": null,
        "value": null
      },
      {
        "stage": "strategy",
        "name": "vwap_relationship",
        "passed": false,
        "detail": null,
        "value": null
      }
    ],
    "final_decision_status": "rejected",
    "final_rejection_reason_code": "target_return_below_threshold",
    "final_rejection_reason_detail": "predicted_return_threshold",
    "notes": []
  },
  {
    "event_id": "e2585231-9706-47de-860e-7335ba47e41e",
    "session_id": "00a83c2f-a276-413c-8e59-4e3f9f49726b",
    "run_id": "430562ad-46d6-47d4-b61b-1ab4d610b826",
    "correlation_id": "3a564bb3-23f3-4903-a713-c284129cb006",
    "timestamp": "2026-03-23T19:59:00Z",
    "strategy": "scalping",
    "strategy_version": "v2",
    "mode": "paper",
    "broker_mode": "alpaca_paper_api",
    "symbol": "USB",
    "side_considered": "buy",
    "bracket_considered": false,
    "signal_source": "qlib_candidate_only",
    "qlib_raw_score": 0.00022255439932498144,
    "predicted_return": 0.00022255439932498144,
    "target_return": 0.00022255439932498144,
    "candidate_rank": 15,
    "prediction_artifact_path": "C:\\Users\\User\\Documents\\MyTradingBot_Next\\models\\predictions\\latest.json",
    "model_artifact_path": "C:\\Users\\User\\Documents\\MyTradingBot_Next\\models\\qlib\\model.pkl",
    "dataset_artifact_path": "C:\\Users\\User\\Documents\\MyTradingBot_Next\\data\\qlib\\dataset.parquet",
    "source_data_timestamp": "2026-03-23T19:59:00Z",
    "source_data_freshness_minutes": 0,
    "rule_checks": [
      {
        "stage": "freshness",
        "name": "predictions_fresh",
        "passed": true,
        "detail": null,
        "value": null
      },
      {
        "stage": "freshness",
        "name": "market_snapshot_fresh",
        "passed": true,
        "detail": null,
        "value": null
      },
      {
        "stage": "strategy",
        "name": "duplicate_position_check",
        "passed": true,
        "detail": null,
        "value": null
      },
      {
        "stage": "strategy",
        "name": "foreign_position_check",
        "passed": true,
        "detail": null,
        "value": null
      },
      {
        "stage": "strategy",
        "name": "cooldown_check",
        "passed": true,
        "detail": null,
        "value": null
      },
      {
        "stage": "strategy",
        "name": "confidence_threshold",
        "passed": false,
        "detail": null,
        "value": null
      },
      {
        "stage": "strategy",
        "name": "cooldown_logic",
        "passed": true,
        "detail": null,
        "value": null
      },
      {
        "stage": "strategy",
        "name": "duplicate_position",
        "passed": true,
        "detail": null,
        "value": null
      },
      {
        "stage": "strategy",
        "name": "flatten_near_close_logic",
        "passed": true,
        "detail": null,
        "value": null
      },
      {
        "stage": "strategy",
        "name": "intraday_volatility_regime",
        "passed": true,
        "detail": null,
        "value": null
      },
      {
        "stage": "strategy",
        "name": "liquidity_filter",
        "passed": true,
        "detail": null,
        "value": null
      },
      {
        "stage": "strategy",
        "name": "liquidity_stress_filter",
        "passed": true,
        "detail": null,
        "value": null
      },
      {
        "stage": "strategy",
        "name": "liquidity_sweep_detection",
        "passed": true,
        "detail": null,
        "value": null
      },
      {
        "stage": "strategy",
        "name": "order_book_imbalance",
        "passed": true,
        "detail": null,
        "value": null
      },
      {
        "stage": "strategy",
        "name": "predicted_return_threshold",
        "passed": false,
        "detail": null,
        "value": null
      },
      {
        "stage": "strategy",
        "name": "qlib_signal_gating",
        "passed": true,
        "detail": null,
        "value": null
      },
      {
        "stage": "strategy",
        "name": "spread_filter",
        "passed": false,
        "detail": null,
        "value": null
      },
      {
        "stage": "strategy",
        "name": "vwap_relationship",
        "passed": true,
        "detail": null,
        "value": null
      }
    ],
    "final_decision_status": "rejected",
    "final_rejection_reason_code": "target_return_below_threshold",
    "final_rejection_reason_detail": "predicted_return_threshold",
    "notes": []
  },
  {
    "event_id": "41375b59-b352-4bc2-87b9-1ac4f4c8ba4f",
    "session_id": "00a83c2f-a276-413c-8e59-4e3f9f49726b",
    "run_id": "430562ad-46d6-47d4-b61b-1ab4d610b826",
    "correlation_id": "a33f74a3-8ec8-4cef-8f0d-26b5abed0af8",
    "timestamp": "2026-03-23T19:59:00Z",
    "strategy": "scalping",
    "strategy_version": "v2",
    "mode": "paper",
    "broker_mode": "alpaca_paper_api",
    "symbol": "NKE",
    "side_considered": "buy",
    "bracket_considered": false,
    "signal_source": "qlib_candidate_only",
    "qlib_raw_score": 0.00021478548898536232,
    "predicted_return": 0.00021478548898536232,
    "target_return": 0.00021478548898536232,
    "candidate_rank": 16,
    "prediction_artifact_path": "C:\\Users\\User\\Documents\\MyTradingBot_Next\\models\\predictions\\latest.json",
    "model_artifact_path": "C:\\Users\\User\\Documents\\MyTradingBot_Next\\models\\qlib\\model.pkl",
    "dataset_artifact_path": "C:\\Users\\User\\Documents\\MyTradingBot_Next\\data\\qlib\\dataset.parquet",
    "source_data_timestamp": "2026-03-23T19:59:00Z",
    "source_data_freshness_minutes": 0,
    "rule_checks": [
      {
        "stage": "freshness",
        "name": "predictions_fresh",
        "passed": true,
        "detail": null,
        "value": null
      },
      {
        "stage": "freshness",
        "name": "market_snapshot_fresh",
        "passed": true,
        "detail": null,
        "value": null
      },
      {
        "stage": "strategy",
        "name": "duplicate_position_check",
        "passed": true,
        "detail": null,
        "value": null
      },
      {
        "stage": "strategy",
        "name": "foreign_position_check",
        "passed": true,
        "detail": null,
        "value": null
      },
      {
        "stage": "strategy",
        "name": "cooldown_check",
        "passed": true,
        "detail": null,
        "value": null
      },
      {
        "stage": "strategy",
        "name": "confidence_threshold",
        "passed": false,
        "detail": null,
        "value": null
      },
      {
        "stage": "strategy",
        "name": "cooldown_logic",
        "passed": true,
        "detail": null,
        "value": null
      },
      {
        "stage": "strategy",
        "name": "duplicate_position",
        "passed": true,
        "detail": null,
        "value": null
      },
      {
        "stage": "strategy",
        "name": "flatten_near_close_logic",
        "passed": true,
        "detail": null,
        "value": null
      },
      {
        "stage": "strategy",
        "name": "intraday_volatility_regime",
        "passed": true,
        "detail": null,
        "value": null
      },
      {
        "stage": "strategy",
        "name": "liquidity_filter",
        "passed": true,
        "detail": null,
        "value": null
      },
      {
        "stage": "strategy",
        "name": "liquidity_stress_filter",
        "passed": true,
        "detail": null,
        "value": null
      },
      {
        "stage": "strategy",
        "name": "liquidity_sweep_detection",
        "passed": true,
        "detail": null,
        "value": null
      },
      {
        "stage": "strategy",
        "name": "order_book_imbalance",
        "passed": true,
        "detail": null,
        "value": null
      },
      {
        "stage": "strategy",
        "name": "predicted_return_threshold",
        "passed": false,
        "detail": null,
        "value": null
      },
      {
        "stage": "strategy",
        "name": "qlib_signal_gating",
        "passed": true,
        "detail": null,
        "value": null
      },
      {
        "stage": "strategy",
        "name": "spread_filter",
        "passed": true,
        "detail": null,
        "value": null
      },
      {
        "stage": "strategy",
        "name": "vwap_relationship",
        "passed": true,
        "detail": null,
        "value": null
      }
    ],
    "final_decision_status": "rejected",
    "final_rejection_reason_code": "target_return_below_threshold",
    "final_rejection_reason_detail": "predicted_return_threshold",
    "notes": []
  },
  {
    "event_id": "da653071-9c76-4394-8058-adfc2808023a",
    "session_id": "00a83c2f-a276-413c-8e59-4e3f9f49726b",
    "run_id": "430562ad-46d6-47d4-b61b-1ab4d610b826",
    "correlation_id": "f54adda7-27d6-4153-98bd-a429f5748139",
    "timestamp": "2026-03-23T19:59:00Z",
    "strategy": "scalping",
    "strategy_version": "v2",
    "mode": "paper",
    "broker_mode": "alpaca_paper_api",
    "symbol": "PINS",
    "side_considered": "buy",
    "bracket_considered": false,
    "signal_source": "qlib_candidate_only",
    "qlib_raw_score": 0.00020600240427168286,
    "predicted_return": 0.00020600240427168286,
    "target_return": 0.00020600240427168286,
    "candidate_rank": 17,
    "prediction_artifact_path": "C:\\Users\\User\\Documents\\MyTradingBot_Next\\models\\predictions\\latest.json",
    "model_artifact_path": "C:\\Users\\User\\Documents\\MyTradingBot_Next\\models\\qlib\\model.pkl",
    "dataset_artifact_path": "C:\\Users\\User\\Documents\\MyTradingBot_Next\\data\\qlib\\dataset.parquet",
    "source_data_timestamp": "2026-03-23T19:59:00Z",
    "source_data_freshness_minutes": 0,
    "rule_checks": [
      {
        "stage": "freshness",
        "name": "predictions_fresh",
        "passed": true,
        "detail": null,
        "value": null
      },
      {
        "stage": "freshness",
        "name": "market_snapshot_fresh",
        "passed": true,
        "detail": null,
        "value": null
      },
      {
        "stage": "strategy",
        "name": "duplicate_position_check",
        "passed": true,
        "detail": null,
        "value": null
      },
      {
        "stage": "strategy",
        "name": "foreign_position_check",
        "passed": true,
        "detail": null,
        "value": null
      },
      {
        "stage": "strategy",
        "name": "cooldown_check",
        "passed": true,
        "detail": null,
        "value": null
      },
      {
        "stage": "strategy",
        "name": "confidence_threshold",
        "passed": false,
        "detail": null,
        "value": null
      },
      {
        "stage": "strategy",
        "name": "cooldown_logic",
        "passed": true,
        "detail": null,
        "value": null
      },
      {
        "stage": "strategy",
        "name": "duplicate_position",
        "passed": true,
        "detail": null,
        "value": null
      },
      {
        "stage": "strategy",
        "name": "flatten_near_close_logic",
        "passed": true,
        "detail": null,
        "value": null
      },
      {
        "stage": "strategy",
        "name": "intraday_volatility_regime",
        "passed": true,
        "detail": null,
        "value": null
      },
      {
        "stage": "strategy",
        "name": "liquidity_filter",
        "passed": true,
        "detail": null,
        "value": null
      },
      {
        "stage": "strategy",
        "name": "liquidity_stress_filter",
        "passed": true,
        "detail": null,
        "value": null
      },
      {
        "stage": "strategy",
        "name": "liquidity_sweep_detection",
        "passed": true,
        "detail": null,
        "value": null
      },
      {
        "stage": "strategy",
        "name": "order_book_imbalance",
        "passed": false,
        "detail": null,
        "value": null
      },
      {
        "stage": "strategy",
        "name": "predicted_return_threshold",
        "passed": false,
        "detail": null,
        "value": null
      },
      {
        "stage": "strategy",
        "name": "qlib_signal_gating",
        "passed": true,
        "detail": null,
        "value": null
      },
      {
        "stage": "strategy",
        "name": "spread_filter",
        "passed": true,
        "detail": null,
        "value": null
      },
      {
        "stage": "strategy",
        "name": "vwap_relationship",
        "passed": false,
        "detail": null,
        "value": null
      }
    ],
    "final_decision_status": "rejected",
    "final_rejection_reason_code": "target_return_below_threshold",
    "final_rejection_reason_detail": "predicted_return_threshold",
    "notes": []
  },
  {
    "event_id": "4f42d312-816b-461e-a707-8353a3f9cddd",
    "session_id": "00a83c2f-a276-413c-8e59-4e3f9f49726b",
    "run_id": "430562ad-46d6-47d4-b61b-1ab4d610b826",
    "correlation_id": "37c41499-3962-4803-b3b6-14e3eae02230",
    "timestamp": "2026-03-23T19:59:00Z",
    "strategy": "scalping",
    "strategy_version": "v2",
    "mode": "paper",
    "broker_mode": "alpaca_paper_api",
    "symbol": "BMNR",
    "side_considered": "buy",
    "bracket_considered": false,
    "signal_source": "qlib_candidate_only",
    "qlib_raw_score": 0.00020566846215637236,
    "predicted_return": 0.00020566846215637236,
    "target_return": 0.00020566846215637236,
    "candidate_rank": 18,
    "prediction_artifact_path": "C:\\Users\\User\\Documents\\MyTradingBot_Next\\models\\predictions\\latest.json",
    "model_artifact_path": "C:\\Users\\User\\Documents\\MyTradingBot_Next\\models\\qlib\\model.pkl",
    "dataset_artifact_path": "C:\\Users\\User\\Documents\\MyTradingBot_Next\\data\\qlib\\dataset.parquet",
    "source_data_timestamp": "2026-03-23T19:59:00Z",
    "source_data_freshness_minutes": 0,
    "rule_checks": [
      {
        "stage": "freshness",
        "name": "predictions_fresh",
        "passed": true,
        "detail": null,
        "value": null
      },
      {
        "stage": "freshness",
        "name": "market_snapshot_fresh",
        "passed": true,
        "detail": null,
        "value": null
      },
      {
        "stage": "strategy",
        "name": "duplicate_position_check",
        "passed": true,
        "detail": null,
        "value": null
      },
      {
        "stage": "strategy",
        "name": "foreign_position_check",
        "passed": true,
        "detail": null,
        "value": null
      },
      {
        "stage": "strategy",
        "name": "cooldown_check",
        "passed": true,
        "detail": null,
        "value": null
      },
      {
        "stage": "strategy",
        "name": "confidence_threshold",
        "passed": false,
        "detail": null,
        "value": null
      },
      {
        "stage": "strategy",
        "name": "cooldown_logic",
        "passed": true,
        "detail": null,
        "value": null
      },
      {
        "stage": "strategy",
        "name": "duplicate_position",
        "passed": true,
        "detail": null,
        "value": null
      },
      {
        "stage": "strategy",
        "name": "flatten_near_close_logic",
        "passed": true,
        "detail": null,
        "value": null
      },
      {
        "stage": "strategy",
        "name": "intraday_volatility_regime",
        "passed": true,
        "detail": null,
        "value": null
      },
      {
        "stage": "strategy",
        "name": "liquidity_filter",
        "passed": true,
        "detail": null,
        "value": null
      },
      {
        "stage": "strategy",
        "name": "liquidity_stress_filter",
        "passed": true,
        "detail": null,
        "value": null
      },
      {
        "stage": "strategy",
        "name": "liquidity_sweep_detection",
        "passed": true,
        "detail": null,
        "value": null
      },
      {
        "stage": "strategy",
        "name": "order_book_imbalance",
        "passed": false,
        "detail": null,
        "value": null
      },
      {
        "stage": "strategy",
        "name": "predicted_return_threshold",
        "passed": false,
        "detail": null,
        "value": null
      },
      {
        "stage": "strategy",
        "name": "qlib_signal_gating",
        "passed": true,
        "detail": null,
        "value": null
      },
      {
        "stage": "strategy",
        "name": "spread_filter",
        "passed": false,
        "detail": null,
        "value": null
      },
      {
        "stage": "strategy",
        "name": "vwap_relationship",
        "passed": false,
        "detail": null,
        "value": null
      }
    ],
    "final_decision_status": "rejected",
    "final_rejection_reason_code": "target_return_below_threshold",
    "final_rejection_reason_detail": "predicted_return_threshold",
    "notes": []
  },
  {
    "event_id": "58efa774-c8a7-429d-9ceb-17c1f1d0281d",
    "session_id": "00a83c2f-a276-413c-8e59-4e3f9f49726b",
    "run_id": "430562ad-46d6-47d4-b61b-1ab4d610b826",
    "correlation_id": "750b9242-0cef-477a-bd97-bd7ef6b8f321",
    "timestamp": "2026-03-23T19:59:00Z",
    "strategy": "scalping",
    "strategy_version": "v2",
    "mode": "paper",
    "broker_mode": "alpaca_paper_api",
    "symbol": "EQT",
    "side_considered": "buy",
    "bracket_considered": false,
    "signal_source": "qlib_candidate_only",
    "qlib_raw_score": 0.00019783517139396558,
    "predicted_return": 0.00019783517139396558,
    "target_return": 0.00019783517139396558,
    "candidate_rank": 19,
    "prediction_artifact_path": "C:\\Users\\User\\Documents\\MyTradingBot_Next\\models\\predictions\\latest.json",
    "model_artifact_path": "C:\\Users\\User\\Documents\\MyTradingBot_Next\\models\\qlib\\model.pkl",
    "dataset_artifact_path": "C:\\Users\\User\\Documents\\MyTradingBot_Next\\data\\qlib\\dataset.parquet",
    "source_data_timestamp": "2026-03-23T19:59:00Z",
    "source_data_freshness_minutes": 0,
    "rule_checks": [
      {
        "stage": "freshness",
        "name": "predictions_fresh",
        "passed": true,
        "detail": null,
        "value": null
      },
      {
        "stage": "freshness",
        "name": "market_snapshot_fresh",
        "passed": true,
        "detail": null,
        "value": null
      },
      {
        "stage": "strategy",
        "name": "duplicate_position_check",
        "passed": true,
        "detail": null,
        "value": null
      },
      {
        "stage": "strategy",
        "name": "foreign_position_check",
        "passed": true,
        "detail": null,
        "value": null
      },
      {
        "stage": "strategy",
        "name": "cooldown_check",
        "passed": true,
        "detail": null,
        "value": null
      },
      {
        "stage": "strategy",
        "name": "confidence_threshold",
        "passed": false,
        "detail": null,
        "value": null
      },
      {
        "stage": "strategy",
        "name": "cooldown_logic",
        "passed": true,
        "detail": null,
        "value": null
      },
      {
        "stage": "strategy",
        "name": "duplicate_position",
        "passed": true,
        "detail": null,
        "value": null
      },
      {
        "stage": "strategy",
        "name": "flatten_near_close_logic",
        "passed": true,
        "detail": null,
        "value": null
      },
      {
        "stage": "strategy",
        "name": "intraday_volatility_regime",
        "passed": true,
        "detail": null,
        "value": null
      },
      {
        "stage": "strategy",
        "name": "liquidity_filter",
        "passed": true,
        "detail": null,
        "value": null
      },
      {
        "stage": "strategy",
        "name": "liquidity_stress_filter",
        "passed": true,
        "detail": null,
        "value": null
      },
      {
        "stage": "strategy",
        "name": "liquidity_sweep_detection",
        "passed": true,
        "detail": null,
        "value": null
      },
      {
        "stage": "strategy",
        "name": "order_book_imbalance",
        "passed": false,
        "detail": null,
        "value": null
      },
      {
        "stage": "strategy",
        "name": "predicted_return_threshold",
        "passed": false,
        "detail": null,
        "value": null
      },
      {
        "stage": "strategy",
        "name": "qlib_signal_gating",
        "passed": true,
        "detail": null,
        "value": null
      },
      {
        "stage": "strategy",
        "name": "spread_filter",
        "passed": false,
        "detail": null,
        "value": null
      },
      {
        "stage": "strategy",
        "name": "vwap_relationship",
        "passed": false,
        "detail": null,
        "value": null
      }
    ],
    "final_decision_status": "rejected",
    "final_rejection_reason_code": "target_return_below_threshold",
    "final_rejection_reason_detail": "predicted_return_threshold",
    "notes": []
  },
  {
    "event_id": "89849bd1-20f3-475b-9a4c-3b7ea7ce204d",
    "session_id": "00a83c2f-a276-413c-8e59-4e3f9f49726b",
    "run_id": "430562ad-46d6-47d4-b61b-1ab4d610b826",
    "correlation_id": "76901a90-21ee-4027-a60b-1361d375b6d0",
    "timestamp": "2026-03-23T19:59:00Z",
    "strategy": "scalping",
    "strategy_version": "v2",
    "mode": "paper",
    "broker_mode": "alpaca_paper_api",
    "symbol": "HOOD",
    "side_considered": "buy",
    "bracket_considered": false,
    "signal_source": "qlib_candidate_only",
    "qlib_raw_score": 0.00018961129791874592,
    "predicted_return": 0.00018961129791874592,
    "target_return": 0.00018961129791874592,
    "candidate_rank": 20,
    "prediction_artifact_path": "C:\\Users\\User\\Documents\\MyTradingBot_Next\\models\\predictions\\latest.json",
    "model_artifact_path": "C:\\Users\\User\\Documents\\MyTradingBot_Next\\models\\qlib\\model.pkl",
    "dataset_artifact_path": "C:\\Users\\User\\Documents\\MyTradingBot_Next\\data\\qlib\\dataset.parquet",
    "source_data_timestamp": "2026-03-23T19:59:00Z",
    "source_data_freshness_minutes": 0,
    "rule_checks": [
      {
        "stage": "freshness",
        "name": "predictions_fresh",
        "passed": true,
        "detail": null,
        "value": null
      },
      {
        "stage": "freshness",
        "name": "market_snapshot_fresh",
        "passed": true,
        "detail": null,
        "value": null
      },
      {
        "stage": "strategy",
        "name": "duplicate_position_check",
        "passed": true,
        "detail": null,
        "value": null
      },
      {
        "stage": "strategy",
        "name": "foreign_position_check",
        "passed": true,
        "detail": null,
        "value": null
      },
      {
        "stage": "strategy",
        "name": "cooldown_check",
        "passed": true,
        "detail": null,
        "value": null
      },
      {
        "stage": "strategy",
        "name": "confidence_threshold",
        "passed": false,
        "detail": null,
        "value": null
      },
      {
        "stage": "strategy",
        "name": "cooldown_logic",
        "passed": true,
        "detail": null,
        "value": null
      },
      {
        "stage": "strategy",
        "name": "duplicate_position",
        "passed": true,
        "detail": null,
        "value": null
      },
      {
        "stage": "strategy",
        "name": "flatten_near_close_logic",
        "passed": true,
        "detail": null,
        "value": null
      },
      {
        "stage": "strategy",
        "name": "intraday_volatility_regime",
        "passed": true,
        "detail": null,
        "value": null
      },
      {
        "stage": "strategy",
        "name": "liquidity_filter",
        "passed": true,
        "detail": null,
        "value": null
      },
      {
        "stage": "strategy",
        "name": "liquidity_stress_filter",
        "passed": true,
        "detail": null,
        "value": null
      },
      {
        "stage": "strategy",
        "name": "liquidity_sweep_detection",
        "passed": true,
        "detail": null,
        "value": null
      },
      {
        "stage": "strategy",
        "name": "order_book_imbalance",
        "passed": false,
        "detail": null,
        "value": null
      },
      {
        "stage": "strategy",
        "name": "predicted_return_threshold",
        "passed": false,
        "detail": null,
        "value": null
      },
      {
        "stage": "strategy",
        "name": "qlib_signal_gating",
        "passed": true,
        "detail": null,
        "value": null
      },
      {
        "stage": "strategy",
        "name": "spread_filter",
        "passed": true,
        "detail": null,
        "value": null
      },
      {
        "stage": "strategy",
        "name": "vwap_relationship",
        "passed": false,
        "detail": null,
        "value": null
      }
    ],
    "final_decision_status": "rejected",
    "final_rejection_reason_code": "target_return_below_threshold",
    "final_rejection_reason_detail": "predicted_return_threshold",
    "notes": []
  }
]